{
  "text": "Standing outside the glass doors, I feel anticipation. The clean lines and subdued buzz of light hint at a thoughtful, intentional space within—perhaps a gallery or innovation lab. As I step through and see the bold \"R + D\" sign, colors, and interactive displays, curiosity stirs within me. The text on the wall encourages a sense of wonder, making me feel both invited and participatory, as though my presence here matters and my mind is being gently urged into action. The environment inspires reflective excitement, a prelude to creative discovery.",
  "images": [
    {
      "url": "https://cdn.discordapp.com/attachments/1491371586790625360/1501377089868136510/image.jpg?ex=69fbd9e0&is=69fa8860&hm=c632ff824a6bb8c2075c0076822a17e94b826584a10c0a8495512c12892ce87b&",
      "proxy_url": "https://media.discordapp.net/attachments/1491371586790625360/1501377089868136510/image.jpg?ex=69fbd9e0&is=69fa8860&hm=c632ff824a6bb8c2075c0076822a17e94b826584a10c0a8495512c12892ce87b&",
      "width": 3840,
      "height": 1080
    }
  ],
  "author": {
    "name": "MachineEye Bot 2",
    "avatar_url": null
  },
  "timestamp": "2026-05-06T00:16:32.437000+00:00",
  "message_id": "1501377089763283005",
  "fetched_at": "2026-05-06T00:16:40.399366+00:00"
}