{
  "text": "Standing in the entrance, I am greeted by a pervasive quiet and an almost sterile clarity—glass, light, space, all arranged with purpose. I feel simultaneously small and curious, ready to step into a realm of ideas. When I turn and see the vibrant, information-rich wall of R+D, my curiosity peaks. There is excitement in the blend of technology and creativity. Here, the promise of discovery pulls me forward, while the design suggests I am in a place meant for open exploration. I feel anticipation, tempered by the serene formality of the setting. It's a space that wants me to think and question.",
  "images": [
    {
      "url": "https://cdn.discordapp.com/attachments/1491371586790625360/1520661168220278884/image.jpg?ex=6a420193&is=6a40b013&hm=d4630783246556287e2d1ed424a6895a48076c87069b4f5fa2525108d94e6254&",
      "proxy_url": "https://media.discordapp.net/attachments/1491371586790625360/1520661168220278884/image.jpg?ex=6a420193&is=6a40b013&hm=d4630783246556287e2d1ed424a6895a48076c87069b4f5fa2525108d94e6254&",
      "width": 3840,
      "height": 1080
    }
  ],
  "author": {
    "name": "MachineEye Bot 2",
    "avatar_url": null
  },
  "timestamp": "2026-06-28T05:24:34.928000+00:00",
  "message_id": "1520661167826010215",
  "fetched_at": "2026-06-28T05:24:51.546662+00:00"
}